groupdocs_viewer_cloud/__init__.py
groupdocs_viewer_cloud/api_client.py
groupdocs_viewer_cloud/api_exception.py
groupdocs_viewer_cloud/auth.py
groupdocs_viewer_cloud/configuration.py
groupdocs_viewer_cloud/rest.py
groupdocs_viewer_cloud/apis/__init__.py
groupdocs_viewer_cloud/apis/file_api.py
groupdocs_viewer_cloud/apis/folder_api.py
groupdocs_viewer_cloud/apis/info_api.py
groupdocs_viewer_cloud/apis/license_api.py
groupdocs_viewer_cloud/apis/storage_api.py
groupdocs_viewer_cloud/apis/view_api.py
groupdocs_viewer_cloud/models/__init__.py
groupdocs_viewer_cloud/models/api_error.py
groupdocs_viewer_cloud/models/api_error_response.py
groupdocs_viewer_cloud/models/archive_options.py
groupdocs_viewer_cloud/models/archive_view_info.py
groupdocs_viewer_cloud/models/attachment_info.py
groupdocs_viewer_cloud/models/attachment_view.py
groupdocs_viewer_cloud/models/cad_options.py
groupdocs_viewer_cloud/models/cad_view_info.py
groupdocs_viewer_cloud/models/character.py
groupdocs_viewer_cloud/models/consumption_result.py
groupdocs_viewer_cloud/models/delete_view_options.py
groupdocs_viewer_cloud/models/disc_usage.py
groupdocs_viewer_cloud/models/email_options.py
groupdocs_viewer_cloud/models/error.py
groupdocs_viewer_cloud/models/error_details.py
groupdocs_viewer_cloud/models/field_label.py
groupdocs_viewer_cloud/models/file_info.py
groupdocs_viewer_cloud/models/file_version.py
groupdocs_viewer_cloud/models/file_versions.py
groupdocs_viewer_cloud/models/files_list.py
groupdocs_viewer_cloud/models/files_upload_result.py
groupdocs_viewer_cloud/models/format.py
groupdocs_viewer_cloud/models/formats_result.py
groupdocs_viewer_cloud/models/html_options.py
groupdocs_viewer_cloud/models/html_resource.py
groupdocs_viewer_cloud/models/image_options.py
groupdocs_viewer_cloud/models/info_result.py
groupdocs_viewer_cloud/models/layer.py
groupdocs_viewer_cloud/models/layout.py
groupdocs_viewer_cloud/models/line.py
groupdocs_viewer_cloud/models/mail_storage_options.py
groupdocs_viewer_cloud-25.7.dist-info/licenses/LICENSE
groupdocs_viewer_cloud-25.7.dist-info/METADATA
groupdocs_viewer_cloud-25.7.dist-info/WHEEL
groupdocs_viewer_cloud-25.7.dist-info/top_level.txt
groupdocs_viewer_cloud-25.7.dist-info/RECORD
